{
    "course_code": "AGRC3518",
    "course_name": "International Agricultural Development",
    "faculty": "Science",
    "school": "Agriculture Food Sciences Schl",
    "units": "2",
    "duration": "One Semester",
    "description": "Agricultural systems and resource use in low-income countries; processes of agricultural and rural development; the agrarian transition and pathways out of rural poverty; policies for agricultural and economic development in a globalised environment. Offered odd years only.",
    "prerequisites": "",
    "incompatible": "ECON3961 or AREC3002",
    "restricted": ""
}