{
    "course_code": "BIOM6301",
    "course_name": "Research Proposal in Biomedical Science",
    "faculty": "Science",
    "school": "Biomedical Sciences School",
    "units": "2",
    "duration": "One Semester",
    "description": "The Research Proposal will be a written report providing an outline of the research to be undertaken as part of the Honours program. The research proposal will include background information in the form of a literature review, aims & significance of the research, expected outcomes, & the methodology/experimental design to be used. This will be undertaken in the first semester as part of the planning for the research project.",
    "prerequisites": "",
    "incompatible": "",
    "restricted": "BSc(Hons) students"
}