{
    "course_code": "CHIN7190",
    "course_name": "Simultaneous Interpreting (English and Mandarin)",
    "faculty": "Humanities and Social Sciences",
    "school": "Languages & Cultures School",
    "units": "2",
    "duration": "One Semester",
    "description": "This course aims to develop students' practical skills in simultaneous interpreting between English and Mandarin at the professional level. It will focus on strategies and techniques required in simultaneous interpreting. The course will expose students to different scenarios in which simultaneous interpreting is used such as legal proceedings, state functions and international conferences. The subject areas for simultaneous interpreting include science and technology, society, business and trade, politics and international relations.",
    "prerequisites": "CHIN7150 or approval by the Program Convenor",
    "incompatible": "",
    "restricted": "Minimum quota: 30"
}