{
    "course_code": "CSSE4080",
    "course_name": "Special Topics in Computer Systems 4A",
    "faculty": "Engineering, Architecture & Information Technology",
    "school": "Info Tech & Elec Engineering",
    "units": "2",
    "duration": "One Semester",
    "description": "Specialist lectures/projects on topical issues in computer systems to be given by visiting lecturers or staff members nominated by Head of School. For details and availability contact enquiries@itee.uq.edu.au.",
    "prerequisites": "Permission of Head of School",
    "incompatible": "",
    "restricted": ""
}