{
    "course_code": "DENT3030",
    "course_name": "Oral Rehabilitation II",
    "faculty": "Health & Behavioural Sciences",
    "school": "Dentistry School",
    "units": "2",
    "duration": "Two Semesters",
    "description": "Management of patients requiring prosthodontic treatment & necessary laboratory work, multi-disciplinary treatment planning & treatment sequencing, development of professional skills & problem solving skills. Provides exposure to removable & implant prosthodontics.",
    "prerequisites": "DENT2030",
    "incompatible": "",
    "restricted": ""
}