{
    "course_code": "ENVM3405",
    "course_name": "Managing Post-Mining Landscapes: Land Rehabilitation in the Mining Industry",
    "faculty": "Science",
    "school": "Earth and Environment Sc Schl",
    "units": "2",
    "duration": "One Semester",
    "description": "Mining and processing of mineral ores and energy resources has significant impacts on both mine sites and operational refinery and processing lands. This course will examine the major land and water impacts of mining and refining activities, and introduce land rehabilitation concepts specific to the management of sites impacted by mining and refining activities. Lectures will be supported by laboratory work to give hands-on analytical experience.",
    "prerequisites": "",
    "incompatible": "ENVM7405",
    "restricted": ""
}