{
    "course_code": "HLTH7115",
    "course_name": "e-Healthcare Research Project",
    "faculty": "Medicine",
    "school": "Medicine Faculty",
    "units": "4",
    "duration": "One Semester",
    "description": "The dissertation shall consist of a 15,000-20,000 assignment on a topic chosen by the student and approved in advance by the supervisor. It may be the result of an original investigation, or embody a critical appraisal or analysis of primary or secondary source material.\n\nHLTH7115 is offered over one semester only.",
    "prerequisites": "",
    "incompatible": "",
    "restricted": ""
}