{
    "course_code": "HRSS4210",
    "course_name": "Health Sciences Research Project: Service Development through Action Learning",
    "faculty": "Health & Behavioural Sciences",
    "school": "Health & Rehab Sci School",
    "units": "2",
    "duration": "One Semester",
    "description": "Practice-based service investigation and development project within a specific field of professional practice in Health Sciences.",
    "prerequisites": "HRSS3102",
    "incompatible": "OCTY4205, HRSS7200",
    "restricted": ""
}