{
    "course_code": "LING1005",
    "course_name": "The Sound Patterns of Language",
    "faculty": "Humanities and Social Sciences",
    "school": "Languages & Cultures School",
    "units": "2",
    "duration": "One Semester",
    "description": "Introduction to basic concepts in linguistics focussing on the sound pattern of language, with English as main language of exemplification. No previous knowledge of subject is assumed.",
    "prerequisites": "",
    "incompatible": "EL102, LING6105",
    "restricted": ""
}