{
    "course_code": "MECH4552",
    "course_name": "Major Design Project",
    "semesters": 1,
    "faculty": "Engineering, Architecture & Information Technology",
    "school": "Mech & Mine Engineering School",
    "units": "4",
    "duration": "Two Semesters",
    "description": "Group design project based on a multidisciplinary topic sponsored by active players in industry (research, academic & commercial organisations). Requires completion of detailed design calculations to the sponsor's specifications.",
    "prerequisites": "#44 toward the BE in the relevant field.",
    "incompatible": "",
    "restricted": ""
}