{
    "course_code": "MGTS1962C",
    "course_name": "Rural Business Management",
    "faculty": "Gatton Vocational Ed Centre",
    "school": "Gatton Vocational Ed Centre",
    "units": "2",
    "duration": "Two Semesters",
    "description": "Introduction to: costing projects; assisting with budget formulation and implementation; and compiling production data. Incorporates graded competencies associated with keeping primary production records, costing projects and operating within a budget framework. Students must enrol in MGTS1962C for both semesters.",
    "prerequisites": "",
    "incompatible": "",
    "restricted": ""
}