{
    "course_code": "MGTS7615",
    "course_name": "Public Sector Accountability",
    "faculty": "Business, Economics & Law",
    "school": "Business School",
    "units": "2",
    "duration": "One Semester",
    "description": "Overview of fundamental elements of the accountability framework governing the public sector, including external controls on administrative discretion and internal controls.",
    "prerequisites": "",
    "incompatible": "",
    "restricted": "Quota: Minimum of 15 enrolments"
}