{
    "course_code": "ORGC2601",
    "course_name": "Influence & Persuasion",
    "faculty": "Business, Economics & Law",
    "school": "Business School",
    "units": "2",
    "duration": "One Semester",
    "description": "This course is designed to enhance students' understanding of the processes and practices central to attitude change, image management and the formation of norms and expectations.",
    "prerequisites": "6 units level 1 courses",
    "incompatible": "",
    "restricted": "Quota: Minimum of 35 enrolments"
}