{
    "course_code": "POLS3802",
    "course_name": "Independent Study",
    "faculty": "Humanities and Social Sciences",
    "school": "Politic Sc & Internat Studies",
    "units": "2",
    "duration": "One Semester",
    "description": "This is a restricted entry course and requires prior approval from the School. The independent study option allows students of exceptional ability to engage in a minor research project. This course can only be undertaken if the planned project is of immediate interest to a potential academic supervisor. Students would be expected to have completed the equivalent of 2 years of full-time study in their undergraduate degree, #12 units of POLS courses with a minimum gpa of 5.5 in these courses. Information about applying to the school to undertake this course is available at : https://polsis.uq.edu.au/student-support",
    "prerequisites": "Two years of full-time study, Six POLS courses and GPA 5.5 >",
    "incompatible": "GT380",
    "restricted": ""
}