{
    "course_code": "TOUR2002",
    "course_name": "Tourism and Leisure Operations Management",
    "faculty": "Business, Economics & Law",
    "school": "Business School",
    "units": "2",
    "duration": "One Semester",
    "description": "This course examines evolving trends of hedonistic services in the tourism and leisure industry sectors. Whilst the major focus is on private sector firms, consideration is given to government influence and involvement.",
    "prerequisites": "",
    "incompatible": "TALM2302 or 2306",
    "restricted": ""
}