{
    "course_code": "CHIN1200",
    "course_name": "Written Chinese IA",
    "faculty": "Humanities and Social Sciences",
    "school": "Languages & Cultures School",
    "units": "2",
    "duration": "One Semester",
    "description": "Reading & writing Chinese characters for students with no prior knowledge of Chinese language. Includes structural analysis of both traditional & simplified characters & important grammatical patterns.\nThis course may be cancelled if there are fewer than 20 enrolments.",
    "prerequisites": "",
    "incompatible": "",
    "restricted": ""
}