{
    "course_code": "CIVL4110",
    "course_name": "Coastal & Estuarine Processes",
    "faculty": "Engineering, Architecture & Information Technology",
    "school": "Civil Engineering School",
    "units": "2",
    "duration": "One Semester",
    "description": "Please Note: this course is only offered in odd-numbered years (eg. 2019). Linear wave theory, short- and long-term wave height statistics, wave spectra, refraction, reflection & diffraction of water waves, wave set up & runup, coastal sediment transport mechanisms, beach morphology & morphodynamics, beach erosion problems & their mitigation, rip currents, longshore currents, surf beat; tides & estuarine mixing.",
    "prerequisites": "",
    "incompatible": "",
    "restricted": ""
}