{
    "course_code": "COMU7311",
    "course_name": "Intercultural Communication",
    "faculty": "Humanities and Social Sciences",
    "school": "Communication & Arts School",
    "units": "2",
    "duration": "One Semester",
    "description": "COMU7311 provides specialised, advanced, and integrated knowledge and skills for research and professional practice in intercultural communication. Students will critically review a complex body of knowledge in intercultural communication, reflect on and synthesise theories and research, apply and transmit knowledge and skills to specialist and non-specialist audiences. The general goal of this course is to equip students with the capacity to demonstrate autonomy, expert judgement, adaptability and responsibility as effective communicators in intercultural contexts.",
    "prerequisites": "",
    "incompatible": "",
    "restricted": ""
}