{
    "course_code": "CRIM3039",
    "course_name": "Advanced Criminological Theory",
    "faculty": "Humanities and Social Sciences",
    "school": "Social Science School",
    "units": "2",
    "duration": "One Semester",
    "description": "Departmental consent is required to enrol in this course - please contact the School for permission to enrol.\nThis course examines major advances in criminological theory over the past century. The course extends knowledge provided in introductory criminology theory and considers current theoretical debates as well as the current research standing of core theories in the field of Criminology. The course provides students with an opportunity to understand the dimensions and complexities of original theoretical statements as well as empirical challenges in testing theories of criminal behaviour.",
    "prerequisites": "CRIM1000, CRIM1019, SOCY2049 or SOCY2019, SOCY2339 and #2 advanced from the criminology major course list",
    "incompatible": "CRIM2029",
    "restricted": ""
}