{
    "course_code": "ECON7700",
    "course_name": "Social Choice & Economic Planning",
    "faculty": "",
    "school": "",
    "units": "2",
    "duration": "One Semester",
    "description": "Not 2007\nProvides an understanding of important social choice issues in modern societies & the economic & related means by which they are being addressed including the benefits & limitations of economic planning/forethought in this process.",
    "prerequisites": "ECON2010 or 7002 or 7010 or 7011 or EC211 or 865",
    "incompatible": "EC877 or 895",
    "restricted": ""
}