{
    "course_code": "ENGG7810",
    "course_name": "Thesis Preparation",
    "faculty": "Engineering, Architecture & Information Technology",
    "school": "Info Tech & Elec Engineering",
    "units": "2",
    "duration": "One Semester",
    "description": "Specialist project undertaken under the supervision of an academic - usually in preparation for a thesis project commencing in a subsequent semester. For details, consult the School of ITEE.",
    "prerequisites": "Permission of Head of School",
    "incompatible": "",
    "restricted": "Restricted to students in the BE/ME integrated degree"
}