{
    "course_code": "LAWS4111",
    "course_name": "Seminars in Jurisprudence",
    "faculty": "Business, Economics & Law",
    "school": "Law School",
    "units": "2",
    "duration": "One Semester",
    "description": "Jurisprudence offers an overview of the historical, doctrinal & philosophical perspectives that have influenced the development of law, together with an introduction to key theoretical positions & interdisciplinary movements that provide critique and commentary on the role of law. Topics include theoretical accounts of the nature of law (including the theories of Hart, Dworkin, Austin, and Kelsen); the central ideas of the natural law tradition, the nature of legal reasoning & the role of the judge; the analytical nature of legal rights & duties; conceptions of justice; the internal organisation of the law; & an introduction to a range of theoretical perspectives of the law, both internal & external.",
    "prerequisites": "All Level 1 & 2 LAWS courses",
    "incompatible": "LAWS2008 or 3704 or 7108",
    "restricted": "LLB(Hons)(#64), LLB(Hons)(#48), LLB(Hons)#64 duals, LLB, LLB duals and LLB (Graduate Entry) programs."
}