{
    "course_code": "OCTY2104",
    "course_name": "Occupational Therapy for Children & Youth I",
    "faculty": "Health & Behavioural Sciences",
    "school": "Health & Rehab Sci School",
    "units": "2",
    "duration": "One Semester",
    "description": "This course addresses occupational therapy practice for children, youth & their families, in relation to a range of developmental, attentional & learning conditions that impact on children's occupational performance & participation. Frames of reference for addressing these issues will be introduced along with appropriate information gathering methods, interventions & models of service delivery. It will also address the participation of children & youth in relation to their home, school and community environments.",
    "prerequisites": "Completed all of Year One of BOccThy (Hons) program",
    "incompatible": "OCTY2100, OCTY2201, OCTY7824",
    "restricted": "Bachelor of Occupational Therapy"
}