{
    "course_code": "PLAN7113",
    "course_name": "Urban Research & Evaluation Techniques",
    "faculty": "Science",
    "school": "Earth and Environment Sc Schl",
    "units": "2",
    "duration": "One Semester",
    "description": "Introduction to broad range of research techniques relevant to planners. Research design, research validity and reliability, survey research, sampling, quantitative and qualitative analysis, stakeholder analysis, ethics.",
    "prerequisites": "",
    "incompatible": "PLAN3001, PLAN4002, ENVM7003",
    "restricted": ""
}