{
    "course_code": "VETS5001",
    "course_name": "Veterinary Surgery & Obstetrics",
    "faculty": "",
    "school": "",
    "units": "2",
    "duration": "Two Semesters",
    "description": "Applied small animal orthopaedics, bovine & small animal obstetrics, degenerative joint diseases, arthrology & fracture management. Small animal surgery rotation for 3 weeks including surgery anaesthesia & radiology including tutorials, practical classes & exposure to clinical cases. Students must enrol in VETS5001 for both semesters.",
    "prerequisites": "Must have completed 32 units of approved courses",
    "incompatible": "",
    "restricted": ""
}